ledes_parser/__init__.py
ledes_parser/ledes_parser.py
ledes_parser/grammars/LEDES98B/line_item.lark
ledes_parser/grammars/LEDES98B/main_grammar.lark
ledes_parser/transformers/__init__.py
ledes_parser/transformers/transformer_1998B.py
ledes_parser-1.5.1.dist-info/LICENSE
ledes_parser-1.5.1.dist-info/METADATA
ledes_parser-1.5.1.dist-info/WHEEL
ledes_parser-1.5.1.dist-info/top_level.txt
ledes_parser-1.5.1.dist-info/RECORD
