Metadata-Version: 2.1
Name: ledes-parser
Version: 1.5.1
Summary: A package for parsing LEDES format files
Home-page: https://github.com/travisbashor/ledes-parser
Author: Travis Bashor
Author-email: travis.bashor@gmail.com
License-File: LICENSE
Requires-Dist: lark-parser ==0.12.0
Requires-Dist: lark ==1.1.9
